enzymm
