Metadata-Version: 2.4
Name: enzymm
Version: 0.1.7
Summary: Detect catalytic enzyme residues in protein structures by matching a library of known templates.
Author-email: Raymund Hackett <r.e.hackett@lumc.nl>
License: MIT License
Project-URL: Bug Tracker, https://github.com/RayHackett/enzymm/issues
Project-URL: Changelog, https://github.com/RayHackett/enzymm/blob/main/CHANGELOG.md
Project-URL: CI, https://github.com/RayHackett/enzymm/actions
Keywords: enzyme,catalytic,active site,protein
Classifier: Development Status :: 4 - Beta
Classifier: Intended Audience :: Developers
Classifier: Intended Audience :: Science/Research
Classifier: License :: OSI Approved :: MIT License
Classifier: Operating System :: OS Independent
Classifier: Programming Language :: Python
Classifier: Programming Language :: Python :: 3
Classifier: Topic :: Software Development :: Libraries :: Python Modules
Classifier: Topic :: Scientific/Engineering :: Bio-Informatics
Classifier: Topic :: Scientific/Engineering :: Chemistry
Classifier: Typing :: Typed
Requires-Python: >=3.7
License-File: LICENSE
Requires-Dist: pyjess~=0.5.2
Requires-Dist: rich>=10.0.0
Requires-Dist: readerwriterlock~=1.0.9
Requires-Dist: importlib-resources>=1.3; python_version < "3.9"
Dynamic: license-file
